hubot_python-0.1.1.dist-info/DESCRIPTION.rst
hubot_python-0.1.1.dist-info/METADATA
hubot_python-0.1.1.dist-info/metadata.json
hubot_python-0.1.1.dist-info/RECORD
hubot_python-0.1.1.dist-info/top_level.txt
hubot_python-0.1.1.dist-info/WHEEL
pybot/__init__.py
pybot/adapter.py
pybot/events.py
pybot/listener.py
pybot/matchers.py
pybot/messages.py
pybot/response.py
pybot/robot.py
pybot/user.py
pybot/adapters/__init__.py
pybot/adapters/shell.py
tests/pybot/__init__.py
tests/pybot/events_tests.py
tests/pybot/listener_tests.py
tests/pybot/matchers_tests.py
tests/pybot/utils.py
