Metadata-Version: 2.0
Name: hubot-python
Version: 0.1.1
Summary: A python port of the popular Hubot
Home-page: https://github.com/jcomo/pybot
Author: Jonathan Como
Author-email: jonathan.como@gmail.com
License: UNKNOWN
Keywords: python chat bot framework automation script
Platform: UNKNOWN
Classifier: Programming Language :: Python :: 2
Classifier: Programming Language :: Python :: 2.6
Classifier: Programming Language :: Python :: 2.7
Classifier: Programming Language :: Python :: 3.3
Classifier: Programming Language :: Python :: 3.4
Requires-Dist: six
